{"cv2denoisedataset_list": ["n20_style1_denoise_sam_msk2", "n20_style2_sci2_sam_msk1"], "threeinputdenoisedataset_list": ["ISTD_Dataset"], "croltroldataset_list": ["Controldata2", "Controldata"], "cv2classdataset_list": ["n6000_shoulder_class"], "cv2segmentdataset_list": ["n6000_shoulder_segment_simple", "USNS"], "cv2segmentdataset_edge_list": [], "cv2segment_cop_class_dataset_list": ["n6000_shoulder_segment_cop_class_simple"], "cv2segmentdataset_lastframe_list": [], "cv2segmentdataset_multitask_list": ["n6000_shoulder_segment_828_multitask"], "cv2segmentdataset_multitask_multiframe_list": ["n6000_shoulder_segment_828_multitask_multiframe"], "npydenoisedataset_list": ["HechengData403ALLnpy"], "sitkdenoisedataset_list": [], "open_cv2_image_class": [], "cv2npysegmentdataset_list": ["UBPB"], "npysegmentdataset_list": ["UBPB"], "cv2srdataset_list": ["DIV2K4xto2x", "DIV2K2x", "DIV2K4x", "set5", "CT0_AREA_X4", "CT0_AREA_UPX4", "CT0_BLUR_K5S1_AREA_X4", "CT0_Random_Cfg1_Down_X4", "DeepLesion_Random_Cfg1_Down_X4", "LDIC_Random_Cfg1_Down_X4", "CT0_fix_cfg1_Down_X4", "DeepLesion_fix_cfg1_Down_X4", "LDIC_fix_cfg1_Down_X4", "LDICSIMPLE_fix_cfg1_Down_X4", "Infer_VitalHuman_AreaDownX4", "LDIC_Fix_cfg2_AreaDownX4", "DeepLesion_Fix_cfg2_AreaDownX4", "CT0_Fix_cfg2_AreaDownX4"]}